champsimextract/__init__.py
champsimextract/common/aggregators.py
champsimextract/common/metrics.py
champsimextract/core/ChampsimLog.py
champsimextract/core/Experiment.py
champsimextract/core/__init__.py
champsimextract/core/metrics.py
champsimextract/core/traces.py
champsimextract/misc/MetricAggr.py
champsimextract/plotting/plotter.py
champsimextract/plotting/tableGen.py
champsimextract-0.2.0.dist-info/METADATA
champsimextract-0.2.0.dist-info/WHEEL
champsimextract-0.2.0.dist-info/top_level.txt
champsimextract-0.2.0.dist-info/RECORD
