Metadata-Version: 2.4
Name: champsimextract
Version: 0.2.0
Summary: A Python toolkit for extracting and visualizing ChampSim simulation results.
Author-email: Shriram Kumar <shriramkumar11152004@gmail.com>
License: MIT
Project-URL: Homepage, https://github.com/KSShriramkumar/ChampSimXtract
Project-URL: Bug Tracker, https://github.com/KSShriramkumar/ChampSimXtract/issues
Keywords: ChampSim,simulation,visualization,architecture
Classifier: Programming Language :: Python :: 3
Classifier: Operating System :: OS Independent
Requires-Python: >=3.8
Requires-Dist: matplotlib
Requires-Dist: numpy
